ewokstxs/__init__.py
ewokstxs/__main__.py
ewokstxs/utils.py
ewokstxs/worker.py
ewokstxs/tasks/__init__.py
ewokstxs/tasks/integrate.py
ewokstxs/tasks/txs.py
ewokstxs/tasks/utils.py
ewokstxs/tests/__init__.py
ewokstxs/tests/conftest.py
ewokstxs/tests/test_TxsTask.py
ewokstxs/tests/test_integrate.py
ewokstxs-0.1.0.dist-info/licenses/LICENSE.md
ewokstxs-0.1.0.dist-info/METADATA
ewokstxs-0.1.0.dist-info/WHEEL
ewokstxs-0.1.0.dist-info/entry_points.txt
ewokstxs-0.1.0.dist-info/top_level.txt
ewokstxs-0.1.0.dist-info/RECORD
