Metadata-Version: 2.4
Name: ewokstxs
Version: 0.1.0
Summary: Data processing workflows for ID09
Author-email: ESRF <dau-pydev@esrf.fr>
License: # MIT License
Project-URL: Homepage, https://gitlab.esrf.fr/workflow/ewoksapps/ewokstxs/
Project-URL: Documentation, https://ewokstxs.readthedocs.io/
Project-URL: Repository, https://gitlab.esrf.fr/workflow/ewoksapps/ewokstxs/
Project-URL: Issues, https://gitlab.esrf.fr/workflow/ewoksapps/ewokstxs/issues
Project-URL: Changelog, https://gitlab.esrf.fr/workflow/ewoksapps/ewokstxs/-/blob/main/CHANGELOG.md
Keywords: ewoks
Classifier: Intended Audience :: Science/Research
Classifier: License :: OSI Approved :: MIT License
Classifier: Programming Language :: Python :: 3
Requires-Python: >=3.10
License-File: LICENSE.md
Requires-Dist: ewoks
Requires-Dist: ewokscore
Requires-Dist: ewoksutils
Requires-Dist: ewoksxrpd[online]>=1.0.0
Requires-Dist: pytxs
Requires-Dist: redis!=5.3.0b1,!=5.3.0b3
Provides-Extra: test
Requires-Dist: pytest>=7; extra == "test"
Requires-Dist: pyqt5; extra == "test"
Provides-Extra: dev
Requires-Dist: ewokstxs[test]; extra == "dev"
Requires-Dist: bandit; extra == "dev"
Requires-Dist: black>=25; extra == "dev"
Requires-Dist: flake8>=4; extra == "dev"
Requires-Dist: mypy; extra == "dev"
Provides-Extra: doc
Requires-Dist: ewokstxs[test]; extra == "doc"
Requires-Dist: sphinx>=4.5; extra == "doc"
Requires-Dist: sphinx-autodoc-typehints>=1.16; extra == "doc"
Requires-Dist: pydata_sphinx_theme; extra == "doc"
Requires-Dist: ewokssphinx; extra == "doc"
Requires-Dist: sphinx-copybutton; extra == "doc"
Dynamic: license-file
